Workbook

Sheet Documentation
A1: Category | B1: Item | C1: Details
A2: Project Overview | B2: Objective | C2: Analyze Q1-Q2 2025 sales data to identify regional trends and product profitability.
B3: Author | C3: Jameizie
B4: Tools Used | C4: Excel (XLOOKUP, Pivot Tables, Conditional Formatting, Power Query)
A5: Data Source | B5: Sales Data | C5: 16-row transactional record including Order ID, Dates, and Financials.
B6: Customer Lookup | C6: Relational table containing Customer Names and Segments.
A7: Data Dictionary | B7: Order ID | C7: Unique transaction identifier (Primary Key).
B8: Region | C8: Geographic sales territory (North, South, East, West).
B9: Category | C9: Product grouping (Furniture, Technology, Office Supplies).
B10: Sales / Profit | C10: Financial metrics in USD ($).
B11: Segment | C11: Customer type joined via XLOOKUP (Consumer, Corporate, Home Office).
A12: Analysis Log | B12: Data Cleaning | C12: Removed duplicate for Order #1006; imputed missing quantity for #1011.
B13: Joins | C13: Performed XLOOKUP on 'Customer ID' to pull Name and Segment into Sales sheet.
B14: Calculations | C14: Defined 'Profit Margin %' as Total Profit / Total Sales.

Sheet Raw_Sales_Data
A1: Order ID | B1: Order Date | C1: Customer ID | D1: Region | E1: Product | F1: Category | G1: Sales | H1: Quantity | I1: Profit
A2: 1001 | B2: 45662 | C2: C-502 | D2: North | E2: Ergo Chair | F2: Furniture | G2: 250 | H2: 2 | I2: 45
A3: 1002 | B3: 45664 | C3: C-501 | D3: West | E3: iPhone 15 | F3: Tech | G3: 999 | H3: 1 | I3: 150
A4: 1003 | B4: 45669 | C4: C-503 | D4: East | E4: Basic Notebook | F4: Office | G4: 5.5 | H4: 10 | I4: 2.1
A5: 1004 | B5: 45672 | C5: C-504 | D5: South | E5: Monitor Stand | F5: Tech | G5: 45 | H5: 1 | I5: 12
A6: 1005 | B6: 45690 | C6: C-502 | D6: North | E6: Desk Lamp | F6: Furniture | G6: 35 | H6: 1 | I6: -5
A7: 1006 | B7: 45698 | C7: C-505 | D7: West | E7: Macbook Pro | F7: Tech | G7: 1800 | H7: 1 | I7: 300
A8: 1006 | B8: 45698 | C8: C-505 | D8: West | E8: Macbook Pro | F8: Tech | G8: 1800 | H8: 1 | I8: 300
A9: 1007 | B9: 45702 | C9: C-501 | D9: West | E9: USB-C Cable | F9: Tech | G9: 15 | H9: 3 | I9: 7.5
A10: 1008 | B10: 45708 | C10: C-506 | D10: East | E10: Coffee Table | F10: Furniture | G10: 120 | H10: 1 | I10: 20
A11: 1009 | B11: 45717 | C11: C-503 | D11: East | E11: Ballpoint Pens | F11: Office | G11: 12 | H11: 5 | I11: 6
A12: 1010 | B12: 45721 | C12: C-504 | D12: South | E12: Wireless Mouse | F12: Tech | G12: 25 | H12: 2 | I12: 10
A13: 1011 | B13: 45731 | C13: C-502 | D13: North | E13: Office Rug | F13: Furniture | G13: 85 | I13: 15
A14: 1012 | B14: 45749 | C14: C-507 | D14: West | E14: Web Cam | F14: Tech | G14: 65 | H14: 1 | I14: 22
A15: 1013 | B15: 45757 | C15: C-508 | D15: North | E15: Paper Shredd. | F15: Office | G15: 110 | H15: 1 | I15: 35
A16: 1014 | B16: 45762 | C16: C-501 | D16: West | E16: iPhone Case | F16: Tech | G16: 25 | H16: 2 | I16: 12
A17: 1015 | B17: 45778 | C17: C-506 | D17: East | E17: Standing Desk | F17: Furniture | G17: 450 | H17: 1 | I17: 80

Sheet Raw_Customer_Lookup
A1: Customer ID | B1: Customer Name | C1: Segment
A2: C-501 | B2: Alice Johnson | C2: Consumer
A3: C-502 | B3: Bob Smith | C3: Corporate
A4: C-503 | B4: Charlie Brown | C4: Home Office
A5: C-504 | B5: David Miller | C5: Consumer
A6: C-505 | B6: Eve Davis | C6: Corporate
A7: C-506 | B7: Frank Wilson | C7: Home Office
A8: C-507 | B8: Grace Lee | C8: Consumer
A9: C-508 | B9: Henry Ford | C9: Corporate

Sheet Data_Processing
A1: Order ID | B1: Order Date | C1: Customer ID | D1: Customer Name | E1: Region | F1: Product | G1: Category | H1: Sales | I1: Quantity | J1: Profit | K1: Segment
A2: 1006 | B2: 45698 | C2: C-505 | D2: =_xlfn.XLOOKUP(C2,Raw_Customer_Lookup!A:A,Raw_Customer_Lookup!B:B) -> Eve Davis | E2: West | F2: Macbook Pro | G2: Tech | H2: 1800 | I2: 1 | J2: 300 | K2: =_xlfn.XLOOKUP(C2,Raw_Customer_Lookup!A:A,Raw_Customer_Lookup!C:C) -> Corporate
A3: 1002 | B3: 45664 | C3: C-501 | D3: =_xlfn.XLOOKUP(C3,Raw_Customer_Lookup!A:A,Raw_Customer_Lookup!B:B) -> Alice Johnson | E3: West | F3: iPhone 15 | G3: Tech | H3: 999 | I3: 1 | J3: 150 | K3: =_xlfn.XLOOKUP(C3,Raw_Customer_Lookup!A:A,Raw_Customer_Lookup!C:C) -> Consumer
A4: 1015 | B4: 45778 | C4: C-506 | D4: =_xlfn.XLOOKUP(C4,Raw_Customer_Lookup!A:A,Raw_Customer_Lookup!B:B) -> Frank Wilson | E4: East | F4: Standing Desk | G4: Furniture | H4: 450 | I4: 1 | J4: 80 | K4: =_xlfn.XLOOKUP(C4,Raw_Customer_Lookup!A:A,Raw_Customer_Lookup!C:C) -> Home Office
A5: 1001 | B5: 45662 | C5: C-502 | D5: =_xlfn.XLOOKUP(C5,Raw_Customer_Lookup!A:A,Raw_Customer_Lookup!B:B) -> Bob Smith | E5: North | F5: Ergo Chair | G5: Furniture | H5: 250 | I5: 2 | J5: 45 | K5: =_xlfn.XLOOKUP(C5,Raw_Customer_Lookup!A:A,Raw_Customer_Lookup!C:C) -> Corporate
A6: 1008 | B6: 45708 | C6: C-506 | D6: =_xlfn.XLOOKUP(C6,Raw_Customer_Lookup!A:A,Raw_Customer_Lookup!B:B) -> Frank Wilson | E6: East | F6: Coffee Table | G6: Furniture | H6: 120 | I6: 1 | J6: 20 | K6: =_xlfn.XLOOKUP(C6,Raw_Customer_Lookup!A:A,Raw_Customer_Lookup!C:C) -> Home Office
A7: 1013 | B7: 45757 | C7: C-508 | D7: =_xlfn.XLOOKUP(C7,Raw_Customer_Lookup!A:A,Raw_Customer_Lookup!B:B) -> Henry Ford | E7: North | F7: Paper Shredd. | G7: Office | H7: 110 | I7: 1 | J7: 35 | K7: =_xlfn.XLOOKUP(C7,Raw_Customer_Lookup!A:A,Raw_Customer_Lookup!C:C) -> Corporate
A8: 1011 | B8: 45731 | C8: C-502 | D8: =_xlfn.XLOOKUP(C8,Raw_Customer_Lookup!A:A,Raw_Customer_Lookup!B:B) -> Bob Smith | E8: North | F8: Office Rug | G8: Furniture | H8: 85 | I8: 1 | J8: 15 | K8: =_xlfn.XLOOKUP(C8,Raw_Customer_Lookup!A:A,Raw_Customer_Lookup!C:C) -> Corporate
A9: 1012 | B9: 45749 | C9: C-507 | D9: =_xlfn.XLOOKUP(C9,Raw_Customer_Lookup!A:A,Raw_Customer_Lookup!B:B) -> Grace Lee | E9: West | F9: Web Cam | G9: Tech | H9: 65 | I9: 1 | J9: 22 | K9: =_xlfn.XLOOKUP(C9,Raw_Customer_Lookup!A:A,Raw_Customer_Lookup!C:C) -> Consumer
A10: 1004 | B10: 45672 | C10: C-504 | D10: =_xlfn.XLOOKUP(C10,Raw_Customer_Lookup!A:A,Raw_Customer_Lookup!B:B) -> David Miller | E10: South | F10: Monitor Stand | G10: Tech | H10: 45 | I10: 1 | J10: 12 | K10: =_xlfn.XLOOKUP(C10,Raw_Customer_Lookup!A:A,Raw_Customer_Lookup!C:C) -> Consumer
A11: 1005 | B11: 45690 | C11: C-502 | D11: =_xlfn.XLOOKUP(C11,Raw_Customer_Lookup!A:A,Raw_Customer_Lookup!B:B) -> Bob Smith | E11: North | F11: Desk Lamp | G11: Furniture | H11: 35 | I11: 1 | J11: -5 | K11: =_xlfn.XLOOKUP(C11,Raw_Customer_Lookup!A:A,Raw_Customer_Lookup!C:C) -> Corporate
A12: 1010 | B12: 45721 | C12: C-504 | D12: =_xlfn.XLOOKUP(C12,Raw_Customer_Lookup!A:A,Raw_Customer_Lookup!B:B) -> David Miller | E12: South | F12: Wireless Mouse | G12: Tech | H12: 25 | I12: 2 | J12: 10 | K12: =_xlfn.XLOOKUP(C12,Raw_Customer_Lookup!A:A,Raw_Customer_Lookup!C:C) -> Consumer
A13: 1014 | B13: 45762 | C13: C-501 | D13: =_xlfn.XLOOKUP(C13,Raw_Customer_Lookup!A:A,Raw_Customer_Lookup!B:B) -> Alice Johnson | E13: West | F13: iPhone Case | G13: Tech | H13: 25 | I13: 2 | J13: 12 | K13: =_xlfn.XLOOKUP(C13,Raw_Customer_Lookup!A:A,Raw_Customer_Lookup!C:C) -> Consumer
... A16: 1003 | B16: 45669 | C16: C-503 | D16: =_xlfn.XLOOKUP(C16,Raw_Customer_Lookup!A:A,Raw_Customer_Lookup!B:B) -> Charlie Brown | E16: East | F16: Basic Notebook | G16: Office | H16: 5.5 | I16: 10 | J16: 2.1 | K16: =_xlfn.XLOOKUP(C16,Raw_Customer_Lookup!A:A,Raw_Customer_Lookup!C:C) -> Home Office

Sheet Pivots_Calculations
A1: Order Date | B1: (All) | D1: Category | E1: (All) | G1: Summary Metrics
G2: Metric | H2: Values
A3: Region | B3: Revenue | D3: Region | E3: Total Orders | G3: Total Sales | H3: =SUM(Data_Processing!H:H) -> 4041.5
A4: West | B4: 2904 | D4: West | E4: 5 | G4: Average Order Value | H4: =AVERAGE(Data_Processing!H:H) -> 269.43333
A5: East | B5: 587.5 | D5: East | E5: 4 | G5: Total Orders | H5: =COUNT(Data_Processing!A:A) -> 15
A6: North | B6: 395 | D6: North | E6: 3 | G6: Highest Sales | H6: =MAX(Data_Processing!H:H) -> 1800
A7: South | B7: 70 | D7: South | E7: 2 | G7: Lowest Sales | H7: =MIN(Data_Processing!H:H) -> 5.5
A8: Grand Total | B8: 3956.5 | D8: Grand Total | E8: 14 | G8: Total Profit | H8: =SUM(Data_Processing!J:J) -> 711.6
G9: Profit Margin | H9: =H8/H3 -> 0.17607324
A10: Products | B10: Revenue
A11: Macbook Pro | B11: 1800 | D11: Category | E11: Total Orders
A12: iPhone 15 | B12: 999 | D12: Tech | E12: 7
A13: Standing Desk | B13: 450 | D13: Furniture | E13: 4
A14: Ergo Chair | B14: 250 | D14: Office | E14: 3
A15: Coffee Table | B15: 120 | D15: Grand Total | E15: 14
A16: Paper Shredd. | B16: 110
A17: Web Cam | B17: 65
A18: Monitor Stand | B18: 45
A19: Desk Lamp | B19: 35 | D19: Month | E19: Revenue
A20: Wireless Mouse | B20: 25 | D20: Jan | E20: 1299.5
A21: iPhone Case | B21: 25 | D21: Feb | E21: 1970
A22: USB-C Cable | B22: 15 | D22: Mar | E22: 37
A23: Ballpoint Pens | B23: 12 | D23: Apr | E23: 200
A24: Basic Notebook | B24: 5.5 | D24: May | E24: 450
A25: Grand Total | B25: 3956.5 | D25: Grand Total | E25: 3956.5

Sheet Insights
A1: Number | B1: Insights
A2: 1 | B2: The West region generates the highest sales, driven largely by high-value tech products like the MacBook Pro and iPhone.
A3: 2 | B3: Tech products produce the largest individual transactions, while Office supplies generate smaller but more frequent orders.
A4: 3 | B4: One product (Desk Lamp) generated negative profit, indicating potential pricing or cost issues.
